setup.py
beans/__init__.py
beans/api.py
beans/exception.py
beans.egg-info/PKG-INFO
beans.egg-info/SOURCES.txt
beans.egg-info/dependency_links.txt
beans.egg-info/requires.txt
beans.egg-info/top_level.txt
test/test.py