Metadata-Version: 1.1
Name: beans
Version: 1.1
Summary: The Python client library for the Beans API
Home-page: https://github.com/loyalbeans/Beans-API-Python
Author: Beans
Author-email: contact@loyalbeans.com
License: Apache
Download-URL: https://github.com/loyalbeans/Beans-API-Python/tarball/v1.1
Platform: UNKNOWN
Classifier: License :: OSI Approved :: Apache Software License
Classifier: Programming Language :: Python
Classifier: Programming Language :: Python :: 2.7
Classifier: Programming Language :: Python :: 3.3
Classifier: Programming Language :: Python :: 3.4
